tests/__init__.py
tests/test_cli.py
xerus/__init__.py
xerus/agent.py
xerus/cli.py
xerus/error_handler.py
xerus/errors.py
xerus/model.py
xerus/sessions.py
xerus/tools.py
xerus/utils.py
xerus/commands/__init__.py
xerus/commands/chat.py
xerus/commands/run.py
xerus/commands/sessions.py
xerus/ui/__init__.py
xerus/ui/display.py
xerus/ui/progress.py
xerus_cli-0.0.2.dist-info/licenses/LICENSE
xerus_cli-0.0.2.dist-info/METADATA
xerus_cli-0.0.2.dist-info/WHEEL
xerus_cli-0.0.2.dist-info/entry_points.txt
xerus_cli-0.0.2.dist-info/top_level.txt
xerus_cli-0.0.2.dist-info/RECORD
