Metadata-Version: 2.4
Name: xerus-cli
Version: 0.0.2
Summary: CLI agent for training and finetuning ML models, built with Huggingface Smolagents
Home-page: https://github.com/ylankgz/xerus
Author: Ulan Abdurazakov
Author-email: ylankgz@gmail.com
Classifier: Programming Language :: Python :: 3
Classifier: License :: OSI Approved :: MIT License
Classifier: Operating System :: OS Independent
Requires-Python: >=3.10
License-File: LICENSE
Requires-Dist: smolagents[litellm,toolkit]>=1.15.0
Requires-Dist: rich-click>=1.8.8
Requires-Dist: python-dotenv>=1.1.0
Dynamic: author
Dynamic: author-email
Dynamic: classifier
Dynamic: description
Dynamic: description-content-type
Dynamic: home-page
Dynamic: license-file
Dynamic: requires-dist
Dynamic: requires-python
Dynamic: summary
